LICENSE
MANIFEST.in
README.md
pyproject.toml
setup.py
src/api_key/__init__.py
src/api_key/admin.py
src/api_key/apps.py
src/api_key/models.py
src/api_key/permissions.py
src/api_key/tests.py
src/api_key/utils.py
src/api_key/migrations/0001_initial.py
src/api_key/migrations/0002_auto_20201007_1716.py
src/api_key/migrations/0003_auto_20220208_1134.py
src/api_key/migrations/__init__.py
src/django_api_key_server.egg-info/PKG-INFO
src/django_api_key_server.egg-info/SOURCES.txt
src/django_api_key_server.egg-info/dependency_links.txt
src/django_api_key_server.egg-info/top_level.txt