Metadata-Version: 2.1
Name: django-api-key-server
Version: 0.1.19
Summary: Use with django-api-key-client
Author: Chunkai Meng
Author-email: willcute@gmail.com
Classifier: Programming Language :: Python :: 3
Classifier: License :: OSI Approved :: MIT License
Classifier: Operating System :: OS Independent
Requires-Python: >=3.6
License-File: LICENSE
